moseh/moseh.py
moseh-0.2.1.dist-info/METADATA
moseh-0.2.1.dist-info/WHEEL
moseh-0.2.1.dist-info/top_level.txt
moseh-0.2.1.dist-info/RECORD
