Metadata-Version: 2.2
Name: moseh
Version: 0.2.1
Summary: Model-Order Selection via Sequential Lagrange Multiplier Hypothesis Testing
Author-email: Gustav Bohlin <guboh@hotmail.com>
License: Apache-2.0
Project-URL: Homepage, https://github.com/guboh/moseh
Project-URL: Bug Tracker, https://github.com/guboh/moseh/issues
Project-URL: Source Code, https://github.com/guboh/moseh
Project-URL: Documentation, https://github.com/guboh/moseh
Classifier: License :: OSI Approved :: Apache Software License
Classifier: Programming Language :: Python :: 3
